[
    {
        "id": 1743231162714,
        "full_name": "hoàng",
        "gender": "Nữ",
        "birthdate": "2006-02-16",
        "hometown": "Hà Nội",
        "permanent_address": "123 Đống Đa, Hà Nội",
        "zone": "B",
        "cell": "B12",
        "visit": "2025-03-29",
        "no_visit": "Không",
        "send": "2006-02-16",
        "arrest_warrant": "123456",
        "arrest_date": "2025-04-20",
        "prison_entry": "2025-05-01",
        "comment": "",
        "note": "",
        "created_by_user": "",
        "created_at": "",
        "updated_by_user": "",
        "updated_at": ""
    },
    {
        "id": 1743231162717,
        "full_name": "Lê Văn Minh Tân 1",
        "gender": "Nữ",
        "birthdate": "2025-03-05",
        "hometown": "Hà Nội",
        "permanent_address": "123 Đống Đa, Hà Nội",
        "zone": "B",
        "cell": "B12",
        "visit": "2025-03-29",
        "no_visit": "Có",
        "send": "2025-03-05",
        "arrest_warrant": "123456",
        "arrest_date": "2025-04-20",
        "prison_entry": "2025-05-01",
        "comment": "",
        "note": "",
        "created_by_user": "",
        "created_at": "",
        "updated_by_user": "",
        "updated_at": ""
    },
    {
        "id": 1743231162718,
        "full_name": "Lê Văn Minh Tân 2323",
        "gender": "Nam",
        "birthdate": "2025-03-05",
        "hometown": "Hà Nội",
        "permanent_address": "123 Đống Đa, Hà Nội",
        "zone": "A",
        "cell": "B12",
        "visit": "2025-03-29",
        "no_visit": "",
        "send": "2025-03-05",
        "arrest_warrant": "123456",
        "arrest_date": "2025-04-20",
        "prison_entry": "2025-05-01",
        "comment": "",
        "note": "",
        "created_by_user": "",
        "created_at": "",
        "updated_by_user": "",
        "updated_at": ""
    },
    {
        "id": 1743231162719,
        "full_name": "Lê Văn Minh Tân 1",
        "gender": "Nữ",
        "birthdate": "2025-03-05",
        "hometown": "Hà Nội",
        "permanent_address": "123 Đống Đa, Hà Nội",
        "zone": "B",
        "cell": "B12",
        "visit": "2025-03-29",
        "no_visit": "",
        "send": "2025-03-05",
        "arrest_warrant": "123456",
        "arrest_date": "2025-04-20",
        "prison_entry": "2025-05-01",
        "comment": "",
        "note": "",
        "created_by_user": "",
        "created_at": "",
        "updated_by_user": "",
        "updated_at": ""
    },
    {
        "id": 1743231162720,
        "full_name": "Lê Văn Minh Tân 2",
        "gender": "Nữ",
        "birthdate": "2025-03-05",
        "hometown": "Hà Nội",
        "permanent_address": "123 Đống Đa, Hà Nội",
        "zone": "C",
        "cell": "B12",
        "visit": "2025-03-29",
        "no_visit": "",
        "send": "2025-03-05",
        "arrest_warrant": "123456",
        "arrest_date": "2025-04-20",
        "prison_entry": "2025-05-01",
        "comment": "",
        "note": "",
        "created_by_user": "",
        "created_at": "",
        "updated_by_user": "",
        "updated_at": ""
    },
    {
        "id": 1743231162721,
        "full_name": "Lê Văn Minh Tân 2323",
        "gender": "Nam",
        "birthdate": "2025-03-05",
        "hometown": "Hà Nội",
        "permanent_address": "123 Đống Đa, Hà Nội",
        "zone": "A",
        "cell": "B12",
        "visit": "2025-03-29",
        "no_visit": "",
        "send": "2025-03-05",
        "arrest_warrant": "123456",
        "arrest_date": "2025-04-20",
        "prison_entry": "2025-05-01",
        "comment": "",
        "note": "",
        "created_by_user": "",
        "created_at": "",
        "updated_by_user": "",
        "updated_at": ""
    },
    {
        "id": 1743231162722,
        "full_name": "Lê Văn Minh Tân 1",
        "gender": "Nữ",
        "birthdate": "2025-03-05",
        "hometown": "Hà Nội",
        "permanent_address": "123 Đống Đa, Hà Nội",
        "zone": "B",
        "cell": "B12",
        "visit": "2025-03-29",
        "no_visit": "",
        "send": "2025-03-05",
        "arrest_warrant": "123456",
        "arrest_date": "2025-04-20",
        "prison_entry": "2025-05-01",
        "comment": "",
        "note": "",
        "created_by_user": "",
        "created_at": "",
        "updated_by_user": "",
        "updated_at": ""
    },
    {
        "id": 1743231162723,
        "full_name": "Lê Văn Minh Tân 2",
        "gender": "Nữ",
        "birthdate": "2025-03-05",
        "hometown": "Hà Nội",
        "permanent_address": "123 Đống Đa, Hà Nội",
        "zone": "C",
        "cell": "B12",
        "visit": "2025-03-29",
        "no_visit": "",
        "send": "2025-03-05",
        "arrest_warrant": "123456",
        "arrest_date": "2025-04-20",
        "prison_entry": "2025-05-01",
        "comment": "",
        "note": "",
        "created_by_user": "",
        "created_at": "",
        "updated_by_user": "",
        "updated_at": ""
    },
    {
        "id": 1743231162724,
        "full_name": "Lê Văn Minh Tân 3",
        "gender": "Nam",
        "birthdate": "2025-03-05",
        "hometown": "Hà Nội",
        "permanent_address": "123 Đống Đa, Hà Nội",
        "zone": "A",
        "cell": "B12",
        "visit": "2025-03-29",
        "no_visit": "",
        "send": "2025-03-05",
        "arrest_warrant": "123456",
        "arrest_date": "2025-04-20",
        "prison_entry": "2025-05-01",
        "comment": "",
        "note": "",
        "created_by_user": "",
        "created_at": "",
        "updated_by_user": "",
        "updated_at": ""
    },
    {
        "id": 1743231162726,
        "full_name": "Lê Văn Minh Tân 1",
        "gender": "Nữ",
        "birthdate": "2025-03-05",
        "hometown": "Hà Nội",
        "permanent_address": "123 Đống Đa, Hà Nội",
        "zone": "B",
        "cell": "B12",
        "visit": "2025-03-29",
        "no_visit": "",
        "send": "2025-03-05",
        "arrest_warrant": "123456",
        "arrest_date": "2025-04-20",
        "prison_entry": "2025-05-01",
        "comment": "",
        "note": "",
        "created_by_user": "",
        "created_at": "",
        "updated_by_user": "",
        "updated_at": ""
    },
    {
        "id": 1743231162727,
        "full_name": "Lê Văn Minh Tân 2",
        "gender": "Nữ",
        "birthdate": "2025-03-05",
        "hometown": "Hà Nội",
        "permanent_address": "123 Đống Đa, Hà Nội",
        "zone": "C",
        "cell": "B12",
        "visit": "2025-03-29",
        "no_visit": "",
        "send": "2025-03-05",
        "arrest_warrant": "123456",
        "arrest_date": "2025-04-20",
        "prison_entry": "2025-05-01",
        "comment": "",
        "note": "",
        "created_by_user": "",
        "created_at": "",
        "updated_by_user": "",
        "updated_at": ""
    },
    {
        "id": 1743231162728,
        "full_name": "Lê Văn Minh Tân 3",
        "gender": "Nam",
        "birthdate": "2025-03-05",
        "hometown": "Hà Nội",
        "permanent_address": "123 Đống Đa, Hà Nội",
        "zone": "A",
        "cell": "B12",
        "visit": "2025-03-29",
        "no_visit": "",
        "send": "2025-03-05",
        "arrest_warrant": "123456",
        "arrest_date": "2025-04-20",
        "prison_entry": "2025-05-01",
        "comment": "",
        "note": "",
        "created_by_user": "",
        "created_at": "",
        "updated_by_user": "",
        "updated_at": ""
    },
    {
        "id": 1743231162729,
        "full_name": "Lê Văn Minh Tân 2323",
        "gender": "Nam",
        "birthdate": "2025-03-05",
        "hometown": "Hà Nội",
        "permanent_address": "123 Đống Đa, Hà Nội",
        "zone": "A",
        "cell": "B12",
        "visit": "2025-03-29",
        "no_visit": "",
        "send": "2025-03-05",
        "arrest_warrant": "123456",
        "arrest_date": "2025-04-20",
        "prison_entry": "2025-05-01",
        "comment": "",
        "note": "",
        "created_by_user": "",
        "created_at": "",
        "updated_by_user": "",
        "updated_at": ""
    },
    {
        "id": 1743231162730,
        "full_name": "Lê Văn Minh Tân 1",
        "gender": "Nữ",
        "birthdate": "2025-03-05",
        "hometown": "Hà Nội",
        "permanent_address": "123 Đống Đa, Hà Nội",
        "zone": "B",
        "cell": "B12",
        "visit": "2025-03-29",
        "no_visit": "",
        "send": "2025-03-05",
        "arrest_warrant": "123456",
        "arrest_date": "2025-04-20",
        "prison_entry": "2025-05-01",
        "comment": "",
        "note": "",
        "created_by_user": "",
        "created_at": "",
        "updated_by_user": "",
        "updated_at": ""
    },
    {
        "id": 1743231162731,
        "full_name": "Lê Văn Minh Tân 2",
        "gender": "Nữ",
        "birthdate": "2025-03-05",
        "hometown": "Hà Nội",
        "permanent_address": "123 Đống Đa, Hà Nội",
        "zone": "C",
        "cell": "B12",
        "visit": "2025-03-29",
        "no_visit": "",
        "send": "2025-03-05",
        "arrest_warrant": "123456",
        "arrest_date": "2025-04-20",
        "prison_entry": "2025-05-01",
        "comment": "",
        "note": "",
        "created_by_user": "",
        "created_at": "",
        "updated_by_user": "",
        "updated_at": ""
    },
    {
        "id": 1743231162732,
        "full_name": "Lê Văn Minh Tân 3",
        "gender": "Nam",
        "birthdate": "2025-03-05",
        "hometown": "Hà Nội",
        "permanent_address": "123 Đống Đa, Hà Nội",
        "zone": "A",
        "cell": "B12",
        "visit": "2025-03-29",
        "no_visit": "",
        "send": "2025-03-05",
        "arrest_warrant": "123456",
        "arrest_date": "2025-04-20",
        "prison_entry": "2025-05-01",
        "comment": "",
        "note": "",
        "created_by_user": "",
        "created_at": "",
        "updated_by_user": "",
        "updated_at": ""
    },
    {
        "id": 1743231162733,
        "full_name": "Lê Văn Minh Tân 2323",
        "gender": "Nam",
        "birthdate": "2025-03-05",
        "hometown": "Hà Nội",
        "permanent_address": "123 Đống Đa, Hà Nội",
        "zone": "A",
        "cell": "B12",
        "visit": "2025-03-29",
        "no_visit": "",
        "send": "2025-03-05",
        "arrest_warrant": "123456",
        "arrest_date": "2025-04-20",
        "prison_entry": "2025-05-01",
        "comment": "",
        "note": "",
        "created_by_user": "",
        "created_at": "",
        "updated_by_user": "",
        "updated_at": ""
    },
    {
        "id": 1743231162734,
        "full_name": "Lê Văn Minh Tân 1",
        "gender": "Nữ",
        "birthdate": "2025-03-05",
        "hometown": "Hà Nội",
        "permanent_address": "123 Đống Đa, Hà Nội",
        "zone": "B",
        "cell": "B12",
        "visit": "2025-03-29",
        "no_visit": "",
        "send": "2025-03-05",
        "arrest_warrant": "123456",
        "arrest_date": "2025-04-20",
        "prison_entry": "2025-05-01",
        "comment": "",
        "note": "",
        "created_by_user": "",
        "created_at": "",
        "updated_by_user": "",
        "updated_at": ""
    },
    {
        "id": 1743231162735,
        "full_name": "Lê Văn Minh Tân 2",
        "gender": "Nữ",
        "birthdate": "2025-03-05",
        "hometown": "Hà Nội",
        "permanent_address": "123 Đống Đa, Hà Nội",
        "zone": "C",
        "cell": "B12",
        "visit": "2025-03-29",
        "no_visit": "",
        "send": "2025-03-05",
        "arrest_warrant": "123456",
        "arrest_date": "2025-04-20",
        "prison_entry": "2025-05-01",
        "comment": "",
        "note": "",
        "created_by_user": "",
        "created_at": "",
        "updated_by_user": "",
        "updated_at": ""
    },
    {
        "id": 1743231162736,
        "full_name": "Lê Văn Minh Tân 3",
        "gender": "Nam",
        "birthdate": "2025-03-05",
        "hometown": "Hà Nội",
        "permanent_address": "123 Đống Đa, Hà Nội",
        "zone": "A",
        "cell": "B12",
        "visit": "2025-03-29",
        "no_visit": "",
        "send": "2025-03-05",
        "arrest_warrant": "123456",
        "arrest_date": "2025-04-20",
        "prison_entry": "2025-05-01",
        "comment": "",
        "note": "",
        "created_by_user": "",
        "created_at": "",
        "updated_by_user": "",
        "updated_at": ""
    },
    {
        "id": 1743231162738,
        "full_name": "zxcxzczx",
        "gender": "Nam",
        "birthdate": "2025-03-28",
        "hometown": "cvcvcv",
        "permanent_address": "cvcbnvn",
        "zone": "cxc",
        "cell": "xcxcxz",
        "visit": "2025-03-27",
        "no_visit": "Có",
        "send": "2025-03-28",
        "arrest_warrant": "cxbcvxv",
        "arrest_date": "2025-03-25",
        "prison_entry": "2025-03-25",
        "comment": "cxvxc3434\nxzcxz\nxzc",
        "note": "cxvcxbxvn555\nzxcxzc\nxzcxzc\nxzc",
        "created_by_user": "",
        "created_at": "",
        "updated_by_user": "",
        "updated_at": ""
    },
    {
        "id": 1743231162739,
        "full_name": "test",
        "gender": "Nam",
        "birthdate": "1999-02-02",
        "hometown": "Huế",
        "permanent_address": "06 Trần Hưng Đạo",
        "zone": "D",
        "cell": "102",
        "visit": "2025-03-26",
        "no_visit": "Không",
        "send": "1999-02-02",
        "arrest_warrant": "1215451",
        "arrest_date": "2025-03-25",
        "prison_entry": "2025-03-27",
        "comment": "xzcmnzxcz\nxzczxc \n",
        "note": "12312\n542352345",
        "created_by_user": "",
        "created_at": "",
        "updated_by_user": "",
        "updated_at": ""
    },
    {
        "id": 1743231203815,
        "full_name": "hoàng",
        "gender": "Nữ",
        "birthdate": "2006-02-16",
        "hometown": "Hà Nội",
        "permanent_address": "123 Đống Đa, Hà Nội",
        "zone": "B",
        "cell": "B12",
        "visit": "2025-03-29",
        "no_visit": "Không",
        "send": "2006-02-16",
        "arrest_warrant": "123456",
        "arrest_date": "2025-04-20",
        "prison_entry": "2025-05-01",
        "comment": "",
        "note": "",
        "created_by_user": "",
        "created_at": "",
        "updated_by_user": "",
        "updated_at": ""
    },
    {
        "id": 1743231203816,
        "full_name": "Lê Văn Minh Tân 1",
        "gender": "Nữ",
        "birthdate": "2025-03-05",
        "hometown": "Hà Nội",
        "permanent_address": "123 Đống Đa, Hà Nội",
        "zone": "B",
        "cell": "B12",
        "visit": "2025-03-29",
        "no_visit": "Có",
        "send": "2025-03-05",
        "arrest_warrant": "123456",
        "arrest_date": "2025-04-20",
        "prison_entry": "2025-05-01",
        "comment": "",
        "note": "",
        "created_by_user": "",
        "created_at": "",
        "updated_by_user": "",
        "updated_at": ""
    },
    {
        "id": 1743231203817,
        "full_name": "Lê Văn Minh Tân 2323",
        "gender": "Nam",
        "birthdate": "2025-03-05",
        "hometown": "Hà Nội",
        "permanent_address": "123 Đống Đa, Hà Nội",
        "zone": "A",
        "cell": "B12",
        "visit": "2025-03-29",
        "no_visit": "",
        "send": "2025-03-05",
        "arrest_warrant": "123456",
        "arrest_date": "2025-04-20",
        "prison_entry": "2025-05-01",
        "comment": "",
        "note": "",
        "created_by_user": "",
        "created_at": "",
        "updated_by_user": "",
        "updated_at": ""
    },
    {
        "id": 1743231203818,
        "full_name": "Lê Văn Minh Tân 1",
        "gender": "Nữ",
        "birthdate": "2025-03-05",
        "hometown": "Hà Nội",
        "permanent_address": "123 Đống Đa, Hà Nội",
        "zone": "B",
        "cell": "B12",
        "visit": "2025-03-29",
        "no_visit": "",
        "send": "2025-03-05",
        "arrest_warrant": "123456",
        "arrest_date": "2025-04-20",
        "prison_entry": "2025-05-01",
        "comment": "",
        "note": "",
        "created_by_user": "",
        "created_at": "",
        "updated_by_user": "",
        "updated_at": ""
    },
    {
        "id": 1743231203819,
        "full_name": "Lê Văn Minh Tân 2",
        "gender": "Nữ",
        "birthdate": "2025-03-05",
        "hometown": "Hà Nội",
        "permanent_address": "123 Đống Đa, Hà Nội",
        "zone": "C",
        "cell": "B12",
        "visit": "2025-03-29",
        "no_visit": "",
        "send": "2025-03-05",
        "arrest_warrant": "123456",
        "arrest_date": "2025-04-20",
        "prison_entry": "2025-05-01",
        "comment": "",
        "note": "",
        "created_by_user": "",
        "created_at": "",
        "updated_by_user": "",
        "updated_at": ""
    },
    {
        "id": 1743231203820,
        "full_name": "Lê Văn Minh Tân 2323",
        "gender": "Nam",
        "birthdate": "2025-03-05",
        "hometown": "Hà Nội",
        "permanent_address": "123 Đống Đa, Hà Nội",
        "zone": "A",
        "cell": "B12",
        "visit": "2025-03-29",
        "no_visit": "",
        "send": "2025-03-05",
        "arrest_warrant": "123456",
        "arrest_date": "2025-04-20",
        "prison_entry": "2025-05-01",
        "comment": "",
        "note": "",
        "created_by_user": "",
        "created_at": "",
        "updated_by_user": "",
        "updated_at": ""
    },
    {
        "id": 1743231203821,
        "full_name": "Lê Văn Minh Tân 1",
        "gender": "Nữ",
        "birthdate": "2025-03-05",
        "hometown": "Hà Nội",
        "permanent_address": "123 Đống Đa, Hà Nội",
        "zone": "B",
        "cell": "B12",
        "visit": "2025-03-29",
        "no_visit": "",
        "send": "2025-03-05",
        "arrest_warrant": "123456",
        "arrest_date": "2025-04-20",
        "prison_entry": "2025-05-01",
        "comment": "",
        "note": "",
        "created_by_user": "",
        "created_at": "",
        "updated_by_user": "",
        "updated_at": ""
    },
    {
        "id": 1743231203822,
        "full_name": "Lê Văn Minh Tân 2",
        "gender": "Nữ",
        "birthdate": "2025-03-05",
        "hometown": "Hà Nội",
        "permanent_address": "123 Đống Đa, Hà Nội",
        "zone": "C",
        "cell": "B12",
        "visit": "2025-03-29",
        "no_visit": "",
        "send": "2025-03-05",
        "arrest_warrant": "123456",
        "arrest_date": "2025-04-20",
        "prison_entry": "2025-05-01",
        "comment": "",
        "note": "",
        "created_by_user": "",
        "created_at": "",
        "updated_by_user": "",
        "updated_at": ""
    },
    {
        "id": 1743231203823,
        "full_name": "Lê Văn Minh Tân 3",
        "gender": "Nam",
        "birthdate": "2025-03-05",
        "hometown": "Hà Nội",
        "permanent_address": "123 Đống Đa, Hà Nội",
        "zone": "A",
        "cell": "B12",
        "visit": "2025-03-29",
        "no_visit": "",
        "send": "2025-03-05",
        "arrest_warrant": "123456",
        "arrest_date": "2025-04-20",
        "prison_entry": "2025-05-01",
        "comment": "",
        "note": "",
        "created_by_user": "",
        "created_at": "",
        "updated_by_user": "",
        "updated_at": ""
    },
    {
        "id": 1743231203824,
        "full_name": "Lê Văn Minh Tân 1",
        "gender": "Nữ",
        "birthdate": "2025-03-05",
        "hometown": "Hà Nội",
        "permanent_address": "123 Đống Đa, Hà Nội",
        "zone": "B",
        "cell": "B12",
        "visit": "2025-03-29",
        "no_visit": "",
        "send": "2025-03-05",
        "arrest_warrant": "123456",
        "arrest_date": "2025-04-20",
        "prison_entry": "2025-05-01",
        "comment": "",
        "note": "",
        "created_by_user": "",
        "created_at": "",
        "updated_by_user": "",
        "updated_at": ""
    },
    {
        "id": 1743231203826,
        "full_name": "Lê Văn Minh Tân 2",
        "gender": "Nữ",
        "birthdate": "2025-03-05",
        "hometown": "Hà Nội",
        "permanent_address": "123 Đống Đa, Hà Nội",
        "zone": "C",
        "cell": "B12",
        "visit": "2025-03-29",
        "no_visit": "",
        "send": "2025-03-05",
        "arrest_warrant": "123456",
        "arrest_date": "2025-04-20",
        "prison_entry": "2025-05-01",
        "comment": "",
        "note": "",
        "created_by_user": "",
        "created_at": "",
        "updated_by_user": "",
        "updated_at": ""
    },
    {
        "id": 1743231203827,
        "full_name": "Lê Văn Minh Tân 3",
        "gender": "Nam",
        "birthdate": "2025-03-05",
        "hometown": "Hà Nội",
        "permanent_address": "123 Đống Đa, Hà Nội",
        "zone": "A",
        "cell": "B12",
        "visit": "2025-03-29",
        "no_visit": "",
        "send": "2025-03-05",
        "arrest_warrant": "123456",
        "arrest_date": "2025-04-20",
        "prison_entry": "2025-05-01",
        "comment": "",
        "note": "",
        "created_by_user": "",
        "created_at": "",
        "updated_by_user": "",
        "updated_at": ""
    },
    {
        "id": 1743231203828,
        "full_name": "Lê Văn Minh Tân 2323",
        "gender": "Nam",
        "birthdate": "2025-03-05",
        "hometown": "Hà Nội",
        "permanent_address": "123 Đống Đa, Hà Nội",
        "zone": "A",
        "cell": "B12",
        "visit": "2025-03-29",
        "no_visit": "",
        "send": "2025-03-05",
        "arrest_warrant": "123456",
        "arrest_date": "2025-04-20",
        "prison_entry": "2025-05-01",
        "comment": "",
        "note": "",
        "created_by_user": "",
        "created_at": "",
        "updated_by_user": "",
        "updated_at": ""
    },
    {
        "id": 1743231203829,
        "full_name": "Lê Văn Minh Tân 1",
        "gender": "Nữ",
        "birthdate": "2025-03-05",
        "hometown": "Hà Nội",
        "permanent_address": "123 Đống Đa, Hà Nội",
        "zone": "B",
        "cell": "B12",
        "visit": "2025-03-29",
        "no_visit": "",
        "send": "2025-03-05",
        "arrest_warrant": "123456",
        "arrest_date": "2025-04-20",
        "prison_entry": "2025-05-01",
        "comment": "",
        "note": "",
        "created_by_user": "",
        "created_at": "",
        "updated_by_user": "",
        "updated_at": ""
    },
    {
        "id": 1743231203830,
        "full_name": "Lê Văn Minh Tân 2",
        "gender": "Nữ",
        "birthdate": "2025-03-05",
        "hometown": "Hà Nội",
        "permanent_address": "123 Đống Đa, Hà Nội",
        "zone": "C",
        "cell": "B12",
        "visit": "2025-03-29",
        "no_visit": "",
        "send": "2025-03-05",
        "arrest_warrant": "123456",
        "arrest_date": "2025-04-20",
        "prison_entry": "2025-05-01",
        "comment": "",
        "note": "",
        "created_by_user": "",
        "created_at": "",
        "updated_by_user": "",
        "updated_at": ""
    },
    {
        "id": 1743231203831,
        "full_name": "Lê Văn Minh Tân 3",
        "gender": "Nam",
        "birthdate": "2025-03-05",
        "hometown": "Hà Nội",
        "permanent_address": "123 Đống Đa, Hà Nội",
        "zone": "A",
        "cell": "B12",
        "visit": "2025-03-29",
        "no_visit": "",
        "send": "2025-03-05",
        "arrest_warrant": "123456",
        "arrest_date": "2025-04-20",
        "prison_entry": "2025-05-01",
        "comment": "",
        "note": "",
        "created_by_user": "",
        "created_at": "",
        "updated_by_user": "",
        "updated_at": ""
    },
    {
        "id": 1743231203832,
        "full_name": "Lê Văn Minh Tân 2323",
        "gender": "Nam",
        "birthdate": "2025-03-05",
        "hometown": "Hà Nội",
        "permanent_address": "123 Đống Đa, Hà Nội",
        "zone": "A",
        "cell": "B12",
        "visit": "2025-03-29",
        "no_visit": "",
        "send": "2025-03-05",
        "arrest_warrant": "123456",
        "arrest_date": "2025-04-20",
        "prison_entry": "2025-05-01",
        "comment": "",
        "note": "",
        "created_by_user": "",
        "created_at": "",
        "updated_by_user": "",
        "updated_at": ""
    },
    {
        "id": 1743231203833,
        "full_name": "Lê Văn Minh Tân 1",
        "gender": "Nữ",
        "birthdate": "2025-03-05",
        "hometown": "Hà Nội",
        "permanent_address": "123 Đống Đa, Hà Nội",
        "zone": "B",
        "cell": "B12",
        "visit": "2025-03-29",
        "no_visit": "",
        "send": "2025-03-05",
        "arrest_warrant": "123456",
        "arrest_date": "2025-04-20",
        "prison_entry": "2025-05-01",
        "comment": "",
        "note": "",
        "created_by_user": "",
        "created_at": "",
        "updated_by_user": "",
        "updated_at": ""
    },
    {
        "id": 1743231203834,
        "full_name": "Lê Văn Minh Tân 2",
        "gender": "Nữ",
        "birthdate": "2025-03-05",
        "hometown": "Hà Nội",
        "permanent_address": "123 Đống Đa, Hà Nội",
        "zone": "C",
        "cell": "B12",
        "visit": "2025-03-29",
        "no_visit": "",
        "send": "2025-03-05",
        "arrest_warrant": "123456",
        "arrest_date": "2025-04-20",
        "prison_entry": "2025-05-01",
        "comment": "",
        "note": "",
        "created_by_user": "",
        "created_at": "",
        "updated_by_user": "",
        "updated_at": ""
    },
    {
        "id": 1743231203835,
        "full_name": "Lê Văn Minh Tân 3",
        "gender": "Nam",
        "birthdate": "2025-03-05",
        "hometown": "Hà Nội",
        "permanent_address": "123 Đống Đa, Hà Nội",
        "zone": "A",
        "cell": "B12",
        "visit": "2025-03-29",
        "no_visit": "",
        "send": "2025-03-05",
        "arrest_warrant": "123456",
        "arrest_date": "2025-04-20",
        "prison_entry": "2025-05-01",
        "comment": "",
        "note": "",
        "created_by_user": "",
        "created_at": "",
        "updated_by_user": "",
        "updated_at": ""
    },
    {
        "id": 1743231203836,
        "full_name": "zxcxzczx",
        "gender": "Nam",
        "birthdate": "2025-03-28",
        "hometown": "cvcvcv",
        "permanent_address": "cvcbnvn",
        "zone": "cxc",
        "cell": "xcxcxz",
        "visit": "2025-03-27",
        "no_visit": "Có",
        "send": "2025-03-28",
        "arrest_warrant": "cxbcvxv",
        "arrest_date": "2025-03-25",
        "prison_entry": "2025-03-25",
        "comment": "cxvxc3434\nxzcxz\nxzc",
        "note": "cxvcxbxvn555\nzxcxzc\nxzcxzc\nxzc",
        "created_by_user": "",
        "created_at": "",
        "updated_by_user": "",
        "updated_at": ""
    },
    {
        "id": 1743231203837,
        "full_name": "test",
        "gender": "Nam",
        "birthdate": "1999-02-02",
        "hometown": "Huế",
        "permanent_address": "06 Trần Hưng Đạo",
        "zone": "D",
        "cell": "102",
        "visit": "2025-03-26",
        "no_visit": "Không",
        "send": "1999-02-02",
        "arrest_warrant": "1215451",
        "arrest_date": "2025-03-25",
        "prison_entry": "2025-03-27",
        "comment": "xzcmnzxcz\nxzczxc \n",
        "note": "12312\n542352345",
        "created_by_user": "",
        "created_at": "",
        "updated_by_user": "",
        "updated_at": ""
    },
    {
        "id": 1743231233193,
        "full_name": "hoàng",
        "gender": "Nữ",
        "birthdate": "2006-02-16",
        "hometown": "Hà Nội",
        "permanent_address": "123 Đống Đa, Hà Nội",
        "zone": "B",
        "cell": "B12",
        "visit": "2025-03-29",
        "no_visit": "Không",
        "send": "2006-02-16",
        "arrest_warrant": "123456",
        "arrest_date": "2025-04-20",
        "prison_entry": "2025-05-01",
        "comment": "",
        "note": "",
        "created_by_user": "",
        "created_at": "",
        "updated_by_user": "",
        "updated_at": ""
    },
    {
        "id": 1743231233194,
        "full_name": "Lê Văn Minh Tân 1",
        "gender": "Nữ",
        "birthdate": "2025-03-05",
        "hometown": "Hà Nội",
        "permanent_address": "123 Đống Đa, Hà Nội",
        "zone": "B",
        "cell": "B12",
        "visit": "2025-03-29",
        "no_visit": "Có",
        "send": "2025-03-05",
        "arrest_warrant": "123456",
        "arrest_date": "2025-04-20",
        "prison_entry": "2025-05-01",
        "comment": "",
        "note": "",
        "created_by_user": "",
        "created_at": "",
        "updated_by_user": "",
        "updated_at": ""
    },
    {
        "id": 1743231233195,
        "full_name": "Lê Văn Minh Tân 2323",
        "gender": "Nam",
        "birthdate": "2025-03-05",
        "hometown": "Hà Nội",
        "permanent_address": "123 Đống Đa, Hà Nội",
        "zone": "A",
        "cell": "B12",
        "visit": "2025-03-29",
        "no_visit": "",
        "send": "2025-03-05",
        "arrest_warrant": "123456",
        "arrest_date": "2025-04-20",
        "prison_entry": "2025-05-01",
        "comment": "",
        "note": "",
        "created_by_user": "",
        "created_at": "",
        "updated_by_user": "",
        "updated_at": ""
    },
    {
        "id": 1743231233196,
        "full_name": "Lê Văn Minh Tân 1",
        "gender": "Nữ",
        "birthdate": "2025-03-05",
        "hometown": "Hà Nội",
        "permanent_address": "123 Đống Đa, Hà Nội",
        "zone": "B",
        "cell": "B12",
        "visit": "2025-03-29",
        "no_visit": "",
        "send": "2025-03-05",
        "arrest_warrant": "123456",
        "arrest_date": "2025-04-20",
        "prison_entry": "2025-05-01",
        "comment": "",
        "note": "",
        "created_by_user": "",
        "created_at": "",
        "updated_by_user": "",
        "updated_at": ""
    },
    {
        "id": 1743231233197,
        "full_name": "Lê Văn Minh Tân 2",
        "gender": "Nữ",
        "birthdate": "2025-03-05",
        "hometown": "Hà Nội",
        "permanent_address": "123 Đống Đa, Hà Nội",
        "zone": "C",
        "cell": "B12",
        "visit": "2025-03-29",
        "no_visit": "",
        "send": "2025-03-05",
        "arrest_warrant": "123456",
        "arrest_date": "2025-04-20",
        "prison_entry": "2025-05-01",
        "comment": "",
        "note": "",
        "created_by_user": "",
        "created_at": "",
        "updated_by_user": "",
        "updated_at": ""
    },
    {
        "id": 1743231233198,
        "full_name": "Lê Văn Minh Tân 2323",
        "gender": "Nam",
        "birthdate": "2025-03-05",
        "hometown": "Hà Nội",
        "permanent_address": "123 Đống Đa, Hà Nội",
        "zone": "A",
        "cell": "B12",
        "visit": "2025-03-29",
        "no_visit": "",
        "send": "2025-03-05",
        "arrest_warrant": "123456",
        "arrest_date": "2025-04-20",
        "prison_entry": "2025-05-01",
        "comment": "",
        "note": "",
        "created_by_user": "",
        "created_at": "",
        "updated_by_user": "",
        "updated_at": ""
    },
    {
        "id": 1743231233199,
        "full_name": "Lê Văn Minh Tân 1",
        "gender": "Nữ",
        "birthdate": "2025-03-05",
        "hometown": "Hà Nội",
        "permanent_address": "123 Đống Đa, Hà Nội",
        "zone": "B",
        "cell": "B12",
        "visit": "2025-03-29",
        "no_visit": "",
        "send": "2025-03-05",
        "arrest_warrant": "123456",
        "arrest_date": "2025-04-20",
        "prison_entry": "2025-05-01",
        "comment": "",
        "note": "",
        "created_by_user": "",
        "created_at": "",
        "updated_by_user": "",
        "updated_at": ""
    },
    {
        "id": 1743231233200,
        "full_name": "Lê Văn Minh Tân 2",
        "gender": "Nữ",
        "birthdate": "2025-03-05",
        "hometown": "Hà Nội",
        "permanent_address": "123 Đống Đa, Hà Nội",
        "zone": "C",
        "cell": "B12",
        "visit": "2025-03-29",
        "no_visit": "",
        "send": "2025-03-05",
        "arrest_warrant": "123456",
        "arrest_date": "2025-04-20",
        "prison_entry": "2025-05-01",
        "comment": "",
        "note": "",
        "created_by_user": "",
        "created_at": "",
        "updated_by_user": "",
        "updated_at": ""
    },
    {
        "id": 1743231233201,
        "full_name": "Lê Văn Minh Tân 3",
        "gender": "Nam",
        "birthdate": "2025-03-05",
        "hometown": "Hà Nội",
        "permanent_address": "123 Đống Đa, Hà Nội",
        "zone": "A",
        "cell": "B12",
        "visit": "2025-03-29",
        "no_visit": "",
        "send": "2025-03-05",
        "arrest_warrant": "123456",
        "arrest_date": "2025-04-20",
        "prison_entry": "2025-05-01",
        "comment": "",
        "note": "",
        "created_by_user": "",
        "created_at": "",
        "updated_by_user": "",
        "updated_at": ""
    },
    {
        "id": 1743231233202,
        "full_name": "Lê Văn Minh Tân 1",
        "gender": "Nữ",
        "birthdate": "2025-03-05",
        "hometown": "Hà Nội",
        "permanent_address": "123 Đống Đa, Hà Nội",
        "zone": "B",
        "cell": "B12",
        "visit": "2025-03-29",
        "no_visit": "",
        "send": "2025-03-05",
        "arrest_warrant": "123456",
        "arrest_date": "2025-04-20",
        "prison_entry": "2025-05-01",
        "comment": "",
        "note": "",
        "created_by_user": "",
        "created_at": "",
        "updated_by_user": "",
        "updated_at": ""
    },
    {
        "id": 1743231233203,
        "full_name": "Lê Văn Minh Tân 2",
        "gender": "Nữ",
        "birthdate": "2025-03-05",
        "hometown": "Hà Nội",
        "permanent_address": "123 Đống Đa, Hà Nội",
        "zone": "C",
        "cell": "B12",
        "visit": "2025-03-29",
        "no_visit": "",
        "send": "2025-03-05",
        "arrest_warrant": "123456",
        "arrest_date": "2025-04-20",
        "prison_entry": "2025-05-01",
        "comment": "",
        "note": "",
        "created_by_user": "",
        "created_at": "",
        "updated_by_user": "",
        "updated_at": ""
    },
    {
        "id": 1743231233204,
        "full_name": "Lê Văn Minh Tân 3",
        "gender": "Nam",
        "birthdate": "2025-03-05",
        "hometown": "Hà Nội",
        "permanent_address": "123 Đống Đa, Hà Nội",
        "zone": "A",
        "cell": "B12",
        "visit": "2025-03-29",
        "no_visit": "",
        "send": "2025-03-05",
        "arrest_warrant": "123456",
        "arrest_date": "2025-04-20",
        "prison_entry": "2025-05-01",
        "comment": "",
        "note": "",
        "created_by_user": "",
        "created_at": "",
        "updated_by_user": "",
        "updated_at": ""
    },
    {
        "id": 1743231233205,
        "full_name": "Lê Văn Minh Tân 2323",
        "gender": "Nam",
        "birthdate": "2025-03-05",
        "hometown": "Hà Nội",
        "permanent_address": "123 Đống Đa, Hà Nội",
        "zone": "A",
        "cell": "B12",
        "visit": "2025-03-29",
        "no_visit": "",
        "send": "2025-03-05",
        "arrest_warrant": "123456",
        "arrest_date": "2025-04-20",
        "prison_entry": "2025-05-01",
        "comment": "",
        "note": "",
        "created_by_user": "",
        "created_at": "",
        "updated_by_user": "",
        "updated_at": ""
    },
    {
        "id": 1743231233206,
        "full_name": "Lê Văn Minh Tân 1",
        "gender": "Nữ",
        "birthdate": "2025-03-05",
        "hometown": "Hà Nội",
        "permanent_address": "123 Đống Đa, Hà Nội",
        "zone": "B",
        "cell": "B12",
        "visit": "2025-03-29",
        "no_visit": "",
        "send": "2025-03-05",
        "arrest_warrant": "123456",
        "arrest_date": "2025-04-20",
        "prison_entry": "2025-05-01",
        "comment": "",
        "note": "",
        "created_by_user": "",
        "created_at": "",
        "updated_by_user": "",
        "updated_at": ""
    },
    {
        "id": 1743231233208,
        "full_name": "Lê Văn Minh Tân 2",
        "gender": "Nữ",
        "birthdate": "2025-03-05",
        "hometown": "Hà Nội",
        "permanent_address": "123 Đống Đa, Hà Nội",
        "zone": "C",
        "cell": "B12",
        "visit": "2025-03-29",
        "no_visit": "",
        "send": "2025-03-05",
        "arrest_warrant": "123456",
        "arrest_date": "2025-04-20",
        "prison_entry": "2025-05-01",
        "comment": "",
        "note": "",
        "created_by_user": "",
        "created_at": "",
        "updated_by_user": "",
        "updated_at": ""
    },
    {
        "id": 1743231233209,
        "full_name": "Lê Văn Minh Tân 3",
        "gender": "Nam",
        "birthdate": "2025-03-05",
        "hometown": "Hà Nội",
        "permanent_address": "123 Đống Đa, Hà Nội",
        "zone": "A",
        "cell": "B12",
        "visit": "2025-03-29",
        "no_visit": "",
        "send": "2025-03-05",
        "arrest_warrant": "123456",
        "arrest_date": "2025-04-20",
        "prison_entry": "2025-05-01",
        "comment": "",
        "note": "",
        "created_by_user": "",
        "created_at": "",
        "updated_by_user": "",
        "updated_at": ""
    },
    {
        "id": 1743231233210,
        "full_name": "Lê Văn Minh Tân 2323",
        "gender": "Nam",
        "birthdate": "2025-03-05",
        "hometown": "Hà Nội",
        "permanent_address": "123 Đống Đa, Hà Nội",
        "zone": "A",
        "cell": "B12",
        "visit": "2025-03-29",
        "no_visit": "",
        "send": "2025-03-05",
        "arrest_warrant": "123456",
        "arrest_date": "2025-04-20",
        "prison_entry": "2025-05-01",
        "comment": "",
        "note": "",
        "created_by_user": "",
        "created_at": "",
        "updated_by_user": "",
        "updated_at": ""
    },
    {
        "id": 1743231233211,
        "full_name": "Lê Văn Minh Tân 1",
        "gender": "Nữ",
        "birthdate": "2025-03-05",
        "hometown": "Hà Nội",
        "permanent_address": "123 Đống Đa, Hà Nội",
        "zone": "B",
        "cell": "B12",
        "visit": "2025-03-29",
        "no_visit": "",
        "send": "2025-03-05",
        "arrest_warrant": "123456",
        "arrest_date": "2025-04-20",
        "prison_entry": "2025-05-01",
        "comment": "",
        "note": "",
        "created_by_user": "",
        "created_at": "",
        "updated_by_user": "",
        "updated_at": ""
    },
    {
        "id": 1743231233212,
        "full_name": "Lê Văn Minh Tân 2",
        "gender": "Nữ",
        "birthdate": "2025-03-05",
        "hometown": "Hà Nội",
        "permanent_address": "123 Đống Đa, Hà Nội",
        "zone": "C",
        "cell": "B12",
        "visit": "2025-03-29",
        "no_visit": "",
        "send": "2025-03-05",
        "arrest_warrant": "123456",
        "arrest_date": "2025-04-20",
        "prison_entry": "2025-05-01",
        "comment": "",
        "note": "",
        "created_by_user": "",
        "created_at": "",
        "updated_by_user": "",
        "updated_at": ""
    },
    {
        "id": 1743231233213,
        "full_name": "Lê Văn Minh Tân 3",
        "gender": "Nam",
        "birthdate": "2025-03-05",
        "hometown": "Hà Nội",
        "permanent_address": "123 Đống Đa, Hà Nội",
        "zone": "A",
        "cell": "B12",
        "visit": "2025-03-29",
        "no_visit": "",
        "send": "2025-03-05",
        "arrest_warrant": "123456",
        "arrest_date": "2025-04-20",
        "prison_entry": "2025-05-01",
        "comment": "",
        "note": "",
        "created_by_user": "",
        "created_at": "",
        "updated_by_user": "",
        "updated_at": ""
    },
    {
        "id": 1743231233214,
        "full_name": "zxcxzczx",
        "gender": "Nam",
        "birthdate": "2025-03-28",
        "hometown": "cvcvcv",
        "permanent_address": "cvcbnvn",
        "zone": "cxc",
        "cell": "xcxcxz",
        "visit": "2025-03-27",
        "no_visit": "Có",
        "send": "2025-03-28",
        "arrest_warrant": "cxbcvxv",
        "arrest_date": "2025-03-25",
        "prison_entry": "2025-03-25",
        "comment": "cxvxc3434\nxzcxz\nxzc",
        "note": "cxvcxbxvn555\nzxcxzc\nxzcxzc\nxzc",
        "created_by_user": "",
        "created_at": "",
        "updated_by_user": "",
        "updated_at": ""
    },
    {
        "id": 1743231233215,
        "full_name": "test",
        "gender": "Nam",
        "birthdate": "1999-02-02",
        "hometown": "Huế",
        "permanent_address": "06 Trần Hưng Đạo",
        "zone": "D",
        "cell": "102",
        "visit": "2025-03-26",
        "no_visit": "Không",
        "send": "1999-02-02",
        "arrest_warrant": "1215451",
        "arrest_date": "2025-03-25",
        "prison_entry": "2025-03-27",
        "comment": "xzcmnzxcz\nxzczxc \n",
        "note": "12312\n542352345",
        "created_by_user": "",
        "created_at": "",
        "updated_by_user": "",
        "updated_at": ""
    }
]